{"commit":"d1a5e1c06dc048bd44ceabb42ddfb28da229e267","pagesAndArtboards":{"CAB6C096-996E-45FC-A937-73BD0AE080E2":{"name":"Page 1","artboards":{"8ACDE25B-55F6-4611-B9CB-34EAC878F04F":{"name":"web"}}}},"version":146,"compatibilityVersion":99,"app":"com.bohemiancoding.sketch3","autosaved":1,"variant":"NONAPPSTORE","coeditCompatibilityVersion":145,"created":{"commit":"d1a5e1c06dc048bd44ceabb42ddfb28da229e267","appVersion":"99.5","build":178873,"app":"com.bohemiancoding.sketch3","coeditCompatibilityVersion":145,"compatibilityVersion":99,"version":146,"variant":"NONAPPSTORE"},"saveHistory":["NONAPPSTORE.178873"],"appVersion":"99.5","build":178873}